[
    {
        "id": "cb5329161aac7489",
        "type": "tab",
        "label": "Flow 1",
        "disabled": false,
        "info": "",
        "env": []
    },
    {
        "id": "c8fe2c3b41c6a9eb",
        "type": "mqtt in",
        "z": "cb5329161aac7489",
        "name": "",
        "topic": "msh/Gateway/2/json/LongFast/!9e9d8770",
        "qos": "0",
        "datatype": "auto-detect",
        "broker": "b4ed02d13afacae4",
        "nl": false,
        "rap": true,
        "rh": 0,
        "inputs": 0,
        "x": 280,
        "y": 160,
        "wires": [
            [
                "74fdeb046922071a",
                "a0793ff748b271d3"
            ]
        ]
    },
    {
        "id": "74fdeb046922071a",
        "type": "switch",
        "z": "cb5329161aac7489",
        "name": "",
        "property": "payload.from",
        "propertyType": "msg",
        "rules": [
            {
                "t": "eq",
                "v": "2661539892",
                "vt": "str"
            }
        ],
        "checkall": "true",
        "repair": false,
        "outputs": 1,
        "x": 570,
        "y": 160,
        "wires": [
            [
                "165178b8860468eb"
            ]
        ]
    },
    {
        "id": "a0793ff748b271d3",
        "type": "debug",
        "z": "cb5329161aac7489",
        "name": "debug 1",
        "active": false,
        "tosidebar": true,
        "console": false,
        "tostatus": false,
        "complete": "payload",
        "targetType": "msg",
        "statusVal": "",
        "statusType": "auto",
        "x": 580,
        "y": 240,
        "wires": []
    },
    {
        "id": "165178b8860468eb",
        "type": "switch",
        "z": "cb5329161aac7489",
        "name": "",
        "property": "payload.type",
        "propertyType": "msg",
        "rules": [
            {
                "t": "eq",
                "v": "telemetry",
                "vt": "str"
            }
        ],
        "checkall": "true",
        "repair": false,
        "outputs": 1,
        "x": 730,
        "y": 160,
        "wires": [
            [
                "671e559c590e34bd",
                "d76c91df786326ae",
                "000a5d55c477d812"
            ]
        ]
    },
    {
        "id": "671e559c590e34bd",
        "type": "function",
        "z": "cb5329161aac7489",
        "name": "function 1",
        "func": "if(msg.payload.payload.hasOwnProperty(\"temperature\")) {\n  node.status({fill:\"blue\",shape:\"ring\",text: msg.payload.payload.temperature.toFixed(1) + \"C\"}); \n}\nreturn msg;",
        "outputs": 1,
        "timeout": 0,
        "noerr": 0,
        "initialize": "",
        "finalize": "",
        "libs": [],
        "x": 1220,
        "y": 160,
        "wires": [
            []
        ]
    },
    {
        "id": "d76c91df786326ae",
        "type": "function",
        "z": "cb5329161aac7489",
        "name": "function 2",
        "func": "if (msg.payload.payload.hasOwnProperty(\"iaq\")) {\n    node.status({ fill: \"blue\", shape: \"ring\", text: msg.payload.payload.iaq.toFixed(1) });\n}\nreturn msg;",
        "outputs": 1,
        "timeout": 0,
        "noerr": 0,
        "initialize": "",
        "finalize": "",
        "libs": [],
        "x": 1220,
        "y": 240,
        "wires": [
            []
        ]
    },
    {
        "id": "000a5d55c477d812",
        "type": "function",
        "z": "cb5329161aac7489",
        "name": "function 3",
        "func": "if (msg.payload.payload.hasOwnProperty(\"gas_resistance\")) {\n    node.status({ fill: \"blue\", shape: \"ring\", text: msg.payload.payload.gas_resistance.toFixed(1) + \"MΩ\" });\n}\nreturn msg;",
        "outputs": 1,
        "timeout": 0,
        "noerr": 0,
        "initialize": "",
        "finalize": "",
        "libs": [],
        "x": 1220,
        "y": 320,
        "wires": [
            []
        ]
    },
    {
        "id": "b4ed02d13afacae4",
        "type": "mqtt-broker",
        "name": "Gateway",
        "broker": "127.0.0.1",
        "port": 1883,
        "clientid": "",
        "autoConnect": true,
        "usetls": false,
        "protocolVersion": 4,
        "keepalive": 60,
        "cleansession": true,
        "autoUnsubscribe": true,
        "birthTopic": "",
        "birthQos": "0",
        "birthRetain": "false",
        "birthPayload": "",
        "birthMsg": {},
        "closeTopic": "",
        "closeQos": "0",
        "closeRetain": "false",
        "closePayload": "",
        "closeMsg": {},
        "willTopic": "",
        "willQos": "0",
        "willRetain": "false",
        "willPayload": "",
        "willMsg": {},
        "userProps": "",
        "sessionExpiry": ""
    }
]